afs/VERSION
afs/__init__.py
afs/_afs/__init__.py
afs/_afs/_base_model.py
afs/_afs/_config.py
afs/_afs/_descriptors.py
afs/_afs/_parser.py
afs/app.py
afs/config.py
afs/functions/__init__.py
afs/functions/aiello/__init__.py
afs/functions/aiello/get_iot_commands.py
afs/functions/assorted/__init__.py
afs/functions/assorted/currencies.py
afs/functions/azure/__init__.py
afs/functions/azure/get_weather_forecast_daily.py
afs/functions/azure/get_weather_forecast_hourly.py
afs/functions/google/__init__.py
afs/functions/google/get_maps_geocode.py
afs/types/__init__.py
afs/types/chat_completion_tool.py
afs/types/chat_completion_tool_message.py
afs/types/pagination.py
afs/types/simple_message.py
afs/types/tool_output.py
afs/utils/__init__.py
afs/utils/display.py
afs/utils/function_definition.py
afs/utils/function_tool.py
afs/utils/get.py
afs/utils/import_.py
afs/utils/instructions.py
afs/utils/logger.py
afs/utils/openai_utils/__init__.py
afs/utils/openai_utils/ensure.py
afs/utils/openai_utils/event_handlers.py
afs/utils/openai_utils/iter_.py
afs/utils/rich_print.py
afs/utils/run.py
afs/version.py
afs_py-0.6.0.dist-info/LICENSE
afs_py-0.6.0.dist-info/METADATA
afs_py-0.6.0.dist-info/WHEEL
afs_py-0.6.0.dist-info/RECORD
