Metadata-Version: 2.1
Name: afs-py
Version: 0.6.0
Summary: Quick define a function compatibility to OpenAI function tool.
License: Private
Author: allen.chou
Author-email: allen.chou@aiello.ai
Requires-Python: >=3.12,<4.0
Classifier: License :: Other/Proprietary License
Classifier: Programming Language :: Python :: 3
Classifier: Programming Language :: Python :: 3.12
Classifier: Programming Language :: Python :: 3.13
Provides-Extra: all
Provides-Extra: svc
Requires-Dist: babel
Requires-Dist: diskcache
Requires-Dist: fastapi[standard] ; extra == "all" or extra == "svc"
Requires-Dist: json_repair
Requires-Dist: loguru ; extra == "all" or extra == "svc"
Requires-Dist: openai (>=1,<2)
Requires-Dist: pycountry
Requires-Dist: pydantic (>=2,<3)
Requires-Dist: pydantic-settings
Requires-Dist: pymongo[srv] ; extra == "all" or extra == "svc"
Requires-Dist: redis (>=5,<6)
